scaling/__init__.py
scaling/utils.py
scaling/data/__init__.py
scaling/data/eads.py
scaling/data/reaction.py
scaling/data/species.py
scaling/plotters/__init__.py
scaling/plotters/correlations.py
scaling/plotters/volcanos.py
scaling/relation/__init__.py
scaling/relation/analysis.py
scaling/relation/builder.py
scaling/relation/descriptors.py
scaling/relation/relation.py
cat_scaling-2024.315b0.dist-info/LICENSE
cat_scaling-2024.315b0.dist-info/METADATA
cat_scaling-2024.315b0.dist-info/WHEEL
cat_scaling-2024.315b0.dist-info/top_level.txt
cat_scaling-2024.315b0.dist-info/RECORD
