Metadata-Version: 2.1
Name: cat-scaling
Version: 2024.315b0
Summary: Build Catalysts Adsorption Energy Scaling Relations
Author-email: "Haoyu(Daniel) Yang" <yanghaoyu97@outlook.com>
License: MIT License
Project-URL: Homepage, https://github.com/DanielYang59/cat-scaling
Keywords: catalysts,adsorption-energy,scaling-relations
Classifier: License :: OSI Approved :: MIT License
Classifier: Programming Language :: Python :: 3
Requires-Python: >=3.9
License-File: LICENSE
Requires-Dist: numpy
Requires-Dist: pandas
Requires-Dist: scikit-learn
Requires-Dist: matplotlib
Provides-Extra: dev
Requires-Dist: pytest ; extra == 'dev'
Requires-Dist: pre-commit ; extra == 'dev'
Requires-Dist: black ; extra == 'dev'
Requires-Dist: isort ; extra == 'dev'
Requires-Dist: bumpver ; extra == 'dev'
